family_tree_viz/__init__.py
family_tree_viz/customised_tree_user.py
family_tree_viz/entities.py
family_tree_viz/family_tree_member.py
family_tree_viz/generator.py
family_tree_viz/relationship_string_simplifier.py
family_tree_viz/renderer.py
family_tree_viz/tree_user.py
family_tree_viz-0.1.0.dist-info/licenses/LICENSE
family_tree_viz-0.1.0.dist-info/METADATA
family_tree_viz-0.1.0.dist-info/WHEEL
family_tree_viz-0.1.0.dist-info/top_level.txt
family_tree_viz-0.1.0.dist-info/RECORD
