Metadata-Version: 2.4
Name: family-tree-viz
Version: 0.1.0
Summary: Python package for visualizing family trees using graphviz.
Author-email: Whispard <whispard.dev@proton.me>
License-Expression: MIT
Project-URL: Homepage, https://github.com/whispard/family-tree-viz
Project-URL: Bug Tracker, https://github.com/whispard/family-tree-viz/issues
Classifier: Programming Language :: Python :: 3
Classifier: Operating System :: OS Independent
Requires-Python: >=3.7
License-File: LICENSE
Requires-Dist: Pillow>=8.0.0
Dynamic: license-file
